frozenlist2/__init__.py
frozenlist2-1.0.0.dist-info/LICENSE
frozenlist2-1.0.0.dist-info/METADATA
frozenlist2-1.0.0.dist-info/WHEEL
frozenlist2-1.0.0.dist-info/top_level.txt
frozenlist2-1.0.0.dist-info/RECORD
