Metadata-Version: 2.1
Name: frozenlist2
Version: 1.0.0
Summary: An immutable list
Home-page: https://github.com/rohanpm/frozenlist2
Author: Rohan McGovern
Author-email: rohan@mcgovern.id.au
License: GNU General Public License
Platform: UNKNOWN
Classifier: Development Status :: 5 - Production/Stable
Classifier: Intended Audience :: Developers
Classifier: License :: OSI Approved :: GNU General Public License v3 or later (GPLv3+)
Classifier: Programming Language :: Python :: 2
Classifier: Programming Language :: Python :: 2.6
Classifier: Programming Language :: Python :: 2.7
Classifier: Programming Language :: Python :: 3
Classifier: Topic :: Software Development :: Libraries :: Python Modules
